MANIFEST.in
README.md
setup.cfg
setup.py
bin/qondor-make-cmssw-tarball
bin/qondor-resubmit
bin/qondor-status
bin/qondor-submit
bin/qondor-version
qondor/__init__.py
qondor/cmsconnect.py
qondor/cmssw.py
qondor/cmssw_releases.py
qondor/logger.py
qondor/resubmit.py
qondor/schedd.py
qondor/submit.py
qondor/svj.py
qondor/utils.py
qondor.egg-info/PKG-INFO
qondor.egg-info/SOURCES.txt
qondor.egg-info/dependency_links.txt
qondor.egg-info/not-zip-safe
qondor.egg-info/requires.txt
qondor.egg-info/top_level.txt
qondor/include/VERSION
qondor/include/scram-pip