Metadata-Version: 1.0
Name: qondor
Version: 1.51
Summary: Description text
Home-page: https://github.com/tklijnsma/qondor.git
Author: Thomas Klijnsma
Author-email: tklijnsm@gmail.com
License: BSD 3-Clause License
Platform: UNKNOWN
